Workbook

Sheet 1 Resumen
B1: Kugelman Academy · Avance comercial de octubre
B2: Marketing y Comercial · Avance de octubre al 23 de octubre de 2026 · Presentación a Dirección y Finanzas
B4: INSCRIPCIONES EN OCTUBRE | F4: CIERRE TRAS CLASE MUESTRA | J4: ASISTENCIA A CLASE MUESTRA | N4: CITAS YA AGENDADAS
B5: =Datos!$B$7 -> 15 | F5: =Datos!$B$10 -> 0.57692308 | J5: =Datos!$B$9 -> 0.66666667 | N5: =Datos!$B$12 -> 20
B7: De 26 prospectos que asistieron a clase muestra (1 al 23-oct). | F7: Campaña de septiembre: 46%. Es nuestra fortaleza. | J7: Campaña de septiembre: 76%. 13 prospectos no llegaron. | N7: 18 del 23 al 29-oct y 2 para el 7-nov. Estimado: ~8 inscripciones.
B9: INVERSIÓN META (4 AL 23-OCT) | F9: COSTO POR CONVERSACIÓN | J9: COSTO POR INSCRIPCIÓN (APARENTE) | N9: BAJAS DEL 1 AL 16-OCT
B10: =Datos!$B$19 -> 3356.23 | F10: =Datos!$B$23 -> 9.0954743 | J10: =Datos!$B$28 -> 223.74867 | N10: =Datos!$B$119 -> 9
B12: Al ritmo actual cerraría octubre en ~$4,699 de $5,000. | F12: 369 conversaciones. Septiembre: $12.39 (−27%). | J12: Septiembre: $304. Se recupera con la primera mensualidad (~$698). | N12: 4 con menos de 17 días inscritos. Salen $6,250 al mes en mensualidades.
B15: Embudo de octubre | J15: Tasas: octubre frente a septiembre
B32: 1. La clase muestra convence | G32: 2. Faltan citas, no interesados | M32: 3. Retener vale más que captar
B33: 58% de quienes asisten se inscribe, más que en septiembre. Cuando el prospecto llega, cerramos. | G33: Hay 47% más conversaciones por día que en septiembre, pero las citas por día no subieron: de cada 100 conversaciones agendan ~11 (septiembre: 16). | M33: Las bajas se llevaron $6,250 de los $10,900 que sumaron las altas. Un alumno cuesta ~$224 y paga ~$698 al mes.

Sheet 2 Embudo y canales
B1: Embudo, canales y segmentos
B2: Marketing y Comercial · Avance de octubre al 23 de octubre de 2026 · Presentación a Dirección y Finanzas
B4: Clases muestra por semana (incluye citas ya agendadas) | K4: Inscritos por canal de origen
B22: Por programa | K22: Inasistencia según horario de la clase
B39: Lectura | J39: Qué haremos
B40: Facebook trae 13 de las 15 inscripciones. Las familias (Kids, Junior y Parenthood) convierten el doble que los adultos: 53% contra 25%. | J40: Confirmar cada cita un día antes y el mismo día, con registro. Las citas de 18 h o más pierden la mitad: hoy se confirman fuera del horario de atención (9 a 18 h).

Sheet 3 Pauta y presupuesto
B1: Inversión publicitaria y propuesta para noviembre
B2: Marketing y Comercial · Avance de octubre al 23 de octubre de 2026 · Presentación a Dirección y Finanzas
B4: GASTADO 4 AL 23-OCT | F4: CIERRE DE OCTUBRE PROYECTADO | J4: CONVERSACIONES | N4: COSTO POR CM REALIZADA
B5: =Datos!$B$19 -> 3356.23 | F5: =Datos!$B$26 -> 0.9397444 | J5: =Datos!$B$20 -> 369 | N5: =Datos!$B$29 -> 129.08577
B7: 168 pesos por día en promedio. | F7: ~$4,699 del presupuesto habitual de $5,000. | J7: +79 entre el 19 y el 23-oct. Costo: $9.10 cada una. | N7: Septiembre: $104. Sube porque se agenda menos por conversación.
B9: Octubre frente a septiembre (variación por día) | K9: Gasto por anuncio (4 al 23-oct)
B26: Escenarios de inscripciones al mes (estimaciones, no pronósticos) | K26: Propuesta de pauta para noviembre: $5,000
B43: Lectura para Finanzas | J43: Pendiente con Finanzas
B44: Con el mismo presupuesto de $5,000, mejorar agendamiento, confirmación y cierre (C) da más inscripciones (~36) que subir a $7,000 sin cambiar el proceso (D, ~32). Primero proceso, después presupuesto. | J44: Costos fijos mensuales (para margen real por grupo), si el gasto de Meta incluye IVA, cobranza real y política de descuentos.

Sheet 4 Seguimiento y agenda
B1: Seguimiento: agenda y prospectos por cerrar
B2: Marketing y Comercial · Avance de octubre al 23 de octubre de 2026 · Presentación a Dirección y Finanzas
B4: CITAS AGENDADAS | F4: CITAS EN LA MAÑANA O SÁBADO | J4: POR CERRAR (ASISTIERON) | N4: INSCRIPCIONES ESPERADAS DE LA AGENDA
B5: =Datos!$B$12 -> 20 | F5: 12 | J5: 12 | N5: =Datos!$B$15 -> 7.8
B7: 10 familias y 10 adultos. | F7: 4 adultos entre semana en la mañana: candidatos para grupos matutinos. | J7: Asistieron en octubre y no se han inscrito. Ya pagamos su captación. | N7: Estimación con las tasas de octubre por segmento. Sube si mejora la asistencia.
B9: Agenda de clases muestra | M9: Citas por día
B10: Fecha | C10: Día | D10: Hora | E10: Prospecto | H10: Programa | I10: Canal | J10: Confirmada
B11: 46318 | C11: Vie | D11: 5:00 p.m. | E11: Montserrat Perdomo | H11: College | I11: WhatsApp | J11: Pendiente
B12: 46319 | C12: Sáb | D12: 9:00 am | E12: Maria Isabel vela Monteclaro | H12: College | I12: Facebook | J12: Pendiente
B13: 46319 | C13: Sáb | D13: 9:00 am | E13: Angel David Agua | H13: Junior | I13: Facebook | J13: Pendiente
B14: 46319 | C14: Sáb | D14: 11:00 am | E14: Aranza Sarahi Garcia Pacheco | H14: Junior | I14: Facebook | J14: Pendiente
B15: 46319 | C15: Sáb | D15: 11:00 am | E15: Alexa Garcia Pacheco | H15: Kids | I15: Facebook | J15: Pendiente
B16: 46319 | C16: Sáb | D16: 11:00 a.m. | E16: Fernanda Mendoza García | H16: Kids | I16: WhatsApp | J16: Pendiente
B17: 46319 | C17: Sáb | D17: 11:00 a.m. | E17: Tadeo Alamilla Téllez | H17: Kids | I17: WhatsApp | J17: Pendiente
B18: 46321 | C18: Lun | D18: 4:00 p.m. | E18: Marley Lizeth Ponce de León | H18: Kids | I18: WhatsApp | J18: Pendiente
B19: 46321 | C19: Lun | D19: 4:00 pm | E19: Ana Victoria Meneses Maqueda | H19: Kids | I19: WhatsApp | J19: Pendiente
B20: 46321 | C20: Lun | D20: 4:00 pm | E20: Mauricio de Jesús Meneses Maqueda | H20: Parenthood | I20: WhatsApp | J20: Pendiente
B21: 46321 | C21: Lun | D21: 5:00 pm | E21: Blanca Almaraz Callado | H21: College | I21: Instagram | J21: Pendiente
B22: 46321 | C22: Lun | D22: 5:00 pm | E22: Iliana Karen | H22: College | I22: WhatsApp | J22: Pendiente
B23: 46322 | C23: Mar | D23: 9 a.m. | E23: Vladimir Chopin | H23: College | I23: WhatsApp | J23: Pendiente | M23: Motivo de no inscripción (octubre)
B24: 46322 | C24: Mar | D24: 9:00 a.m. | E24: Nidelson Hernandez | H24: College | I24: Facebook | J24: Pendiente
B25: 46322 | C25: Mar | D25: 10:00 a.m. | E25: María Roldán | H25: College | I25: Facebook | J25: Pendiente
B26: 46322 | C26: Mar | D26: 10:00 am | E26: Fernanda Hernandez Alvarado | H26: College | I26: Instagram | J26: Pendiente
B27: 46322 | C27: Mar | D27: 6:00 p.m. | E27: Lizeth Gonzalez Aquino | H27: College | I27: WhatsApp | J27: Pendiente
B28: 46324 | C28: Jue | D28: 6:00 p.m. | E28: Karen León | H28: College | I28: WhatsApp | J28: Pendiente
B29: 46333 | C29: Sáb | E29: Emir | H29: Parenthood | I29: Facebook | J29: Pendiente
B30: 46333 | C30: Sáb | E30: Yarentzy | H30: Kids | I30: Facebook | J30: Pendiente
B32: Asistieron y no se han inscrito: lista de cierre
B33: Fecha CM | C33: Prospecto | F33: Programa | G33: Canal | H33: Motivo registrado | K33: Estatus
B34: 46296 | C34: Claudia Perez | F34: College | G34: Facebook | H34: Sin respuesta | K34: Por contactar
B35: 46301 | C35: Ximena Sanchez Bautista | F35: College | G35: WhatsApp | H35: Inscripción pospuesta | K35: Por contactar
B36: 46304 | C36: Said Emmanuel Hernandez | F36: College | G36: Instagram | H36: Inscripción pospuesta | K36: Por contactar
B37: 46307 | C37: Herlinda Guadalupe Zapataq Molina | F37: Kids | G37: Facebook | H37: Horarios | K37: Por contactar
B38: 46310 | C38: Citlali Perez Vargas | F38: College | G38: Instagram | H38: Horarios | K38: Por contactar
B39: 46310 | C39: Carlos Villalva | F39: Junior | G39: WhatsApp | H39: Horarios | K39: Por contactar
B40: 46310 | C40: Valentina Villalba | F40: Junior | G40: WhatsApp | H40: Horarios | K40: Por contactar
B41: 46311 | C41: Brisa Azul Salgado Anastasio | F41: Junior | G41: WhatsApp | H41: Pendiente de decisión | K41: Por contactar
B42: 46314 | C42: Kim Yetzali | F42: Junior | G42: Facebook | H42: Sin respuesta | K42: Por contactar
B43: 46317 | C43: Eduardo Alexis Vallejo Salazar | F43: College | G43: WhatsApp | H43: Pendiente de decisión | K43: Por contactar
B44: 46317 | C44: Montserrat Hernández Anastasio | F44: College | G44: WhatsApp | H44: Sin motivo | K44: Por contactar
B45: 46307 | C45: Mía Ayelen Vázquez Zapata | F45: Kids | G45: Facebook | H45: Sin registro en el control | K45: Por contactar

Sheet 5 Retencion y capacidad
B1: Retención y capacidad: dónde está la rentabilidad
B2: Marketing y Comercial · Avance de octubre al 23 de octubre de 2026 · Presentación a Dirección y Finanzas · Bajas al 16-oct, base de alumnos al 19-oct
B4: MENSUALIDAD QUE ENTRÓ (ALTAS) | F4: MENSUALIDAD QUE SALIÓ (BAJAS) | J4: SALDO NETO MENSUAL | N4: LUGARES LIBRES EN GRUPOS ACTUALES
B5: =Datos!$B$122 -> 10900 | F5: =Datos!$B$121 -> 6250 | J5: =Datos!$B$123 -> 4650 | N5: =Datos!$B$125 -> 147
B7: Altas del 1 al 15-oct en la base de alumnos. | F7: 9 bajas del 1 al 16-oct; 4 con menos de 17 días. | J7: Las bajas se llevaron más de la mitad de lo ganado. | N7: Ocupación 47%. Llenarlos no cuesta docente adicional.
B9: Lo que entra y lo que sale | H9: Motivos de baja | M9: Ocupación por franja
B25: Lo que vale un alumno | J25: Acción de retención
B26: Costo docente de un grupo: ~$1,733 al mes; se cubre con 3 alumnos. Un alumno extra en un grupo con lugar aporta su mensualidad completa (~$698) y recupera su costo de captación (~$224) en el primer mes. | J26: Llamada en la semana 1 y la semana 3 de cada alumno nuevo, empezando por adultos. Llamar a las 4 bajas temporales con propuesta de horario. Hoy el único contacto ocurre el día de la baja.

Sheet 6 Acciones y decisiones
B1: Avance, acciones y decisiones
B2: Marketing y Comercial · Avance de octubre al 23 de octubre de 2026 · Presentación a Dirección y Finanzas
B4: Avance y plan de acción (actualiza la columna Estatus antes de presentar)
B5: Acción | K5: Responsable | N5: Fecha | P5: Estatus
B6: Control de clases muestra con nivel, agenda de noviembre y reporte automático por mes | K6: Atención comercial | N6: Oct | P6: Hecho
B7: Herramientas listas: sistema de seguimiento, tablero, análisis de inversión y plan de estrategias | K7: Marketing | N7: Oct | P7: Hecho
B8: Agenda de 20 clases muestra del 23-oct al 7-nov | K8: Atención comercial | N8: Oct-nov | P8: En curso
B9: Confirmar cada cita un día antes y el mismo día, y registrar la confirmación | K9: Atención comercial | N9: Desde 24-oct | P9: Por iniciar
B10: Llamada de cierre a los 12 prospectos que asistieron y no se inscribieron | K10: Atención comercial | N10: 24 al 28-oct | P10: Por confirmar
B11: Confirmar pago y alta en la base de Carlos Mercado, Luna Ángeles y Dylan López | K11: Administración | N11: 24-oct | P11: Por confirmar
B12: Arrancar el sistema de seguimiento con fecha de primer contacto y teléfono obligatorio | K12: Comercial | N12: 26-oct | P12: Por iniciar
B13: Check-in en semana 1 y 3 a alumnos nuevos; llamar a las 4 bajas temporales | K13: Comercial + Académico | N13: Desde 26-oct | P13: Por iniciar
B14: Renovar la pauta al terminar la campaña actual (2-nov): $5,000 en dos conjuntos | K14: Marketing + Finanzas | N14: 2-nov | P14: Propuesta
B15: Primer mensaje con dos horarios con cupo, en lugar de solo información | K15: Atención comercial | N15: 2-nov | P15: Propuesta
B16: Programa de recomendación de alumnos y padres | K16: Comercial + Finanzas | N16: 9-nov | P16: Propuesta
B17: Alianzas con escuelas cercanas y clase abierta de sábado (21-nov) | K17: Comercial + Dirección | N17: Nov | P17: Propuesta
B19: Decisiones que pedimos hoy
B20: Área | E20: Decisión | P20: Fecha
B21: Finanzas | E21: Aprobar $5,000 de Meta Ads para noviembre: $2,500 familias, $2,000 adultos-mañana, $500 pruebas. | P21: Antes del 2-nov
B22: Dirección | E22: Cubrir la atención de mensajes y confirmaciones de 18 a 20 h y sábados. | P22: Antes del 2-nov
B23: Finanzas | E23: Beneficio de recomendación: $200 cuando el recomendado paga su segundo mes. | P23: 9-nov
B24: Dirección + Finanzas | E24: Costo docente de talleres en escuelas y clases abiertas: $200 por sesión ($2,800 de nov a mar). | P24: 9-nov
B25: Finanzas | E25: Compartir costos fijos, cobranza real y política de descuentos. | P25: 15-nov
B26: Dirección | E26: Aprobar las metas propuestas: asistencia 75%, cierre 55%, cero bajas antes de 30 días. | P26: Antes del 2-nov

Sheet Datos
A1: Datos del dashboard (corte 23-oct-2026). Las tarjetas y gráficas de las pantallas leen estas celdas: si un dato cambia, cámbialo aquí.
A3: A. Indicadores principales
A4: CM vencidas de prospectos nuevos (1 al 23-oct) | B4: 39 | G4: Control de clases muestra 23-oct; excluye 3 alumnas actuales (francés)
A5: CM realizadas (asistió) | B5: 26
A6: Inasistencias | B6: 13
A7: Inscripciones (pagó 1er mes) | B7: 15 | G7: 3 de ellas (19 y 20-oct) aún no están en la base de alumnos
A8: Asistieron y no se han inscrito | B8: 11
A9: Asistencia | B9: =Datos!$B$5/Datos!$B$4 -> 0.66666667
A10: Cierre tras CM | B10: =Datos!$B$7/Datos!$B$5 -> 0.57692308
A11: CM vencida → inscripción | B11: =Datos!$B$7/Datos!$B$4 -> 0.38461538
A12: Citas agendadas (23-oct a 7-nov) | B12: 20
A13: de ellas en octubre | B13: 18
A14: de ellas en noviembre | B14: 2
A15: Inscripciones esperadas de la agenda (estimación) | B15: 7.8 | G15: Tasa CM vencida → inscripción de octubre por segmento
A16: Inscripciones proyectadas al cierre de octubre (estimación) | B16: =Datos!$B$7+6.71 -> 21.710526
A18: B. Pauta Meta Ads
A19: Gasto Meta Ads 4 al 23-oct | B19: 3356.23 | G19: Exportación Meta Ads 4-23 oct
A20: Conversaciones 4 al 23-oct | B20: 369
A21: Días del reporte | B21: 20
A22: Presupuesto mensual habitual | B22: 5000 | G22: Dato de la academia
A23: Costo por conversación | B23: =Datos!$B$19/Datos!$B$20 -> 9.0954743
A24: Gasto por día | B24: =Datos!$B$19/Datos!$B$21 -> 167.8115
A25: Gasto proyectado 4 al 31-oct (mismo ritmo) | B25: =Datos!$B$19+Datos!$B$24*8 -> 4698.722
A26: % del presupuesto (proyectado) | B26: =Datos!$B$25/Datos!$B$22 -> 0.9397444
A27: Inscritos que llegaron por redes | B27: 15
A28: Costo por inscripción (aparente) | B28: =Datos!$B$19/Datos!$B$27 -> 223.74867
A29: Costo por CM realizada | B29: =Datos!$B$19/Datos!$B$5 -> 129.08577
A31: C. Comparativo (tasas)
A32: Indicador | B32: Campaña sept. (21-ago a 4-oct) | C32: Septiembre 1 al 23 (control) | D32: Octubre 1 al 23
A33: Asistencia | B33: 0.76136364 | C33: 0.78125 | D33: 0.66666667
A34: Cierre tras CM | B34: 0.462 | C34: 0.52 | D34: 0.57692308
A35: CM vencida → inscripción | B35: 0.34090909 | C35: 0.40625 | D35: 0.38461538
A36: Volumen | B36: Campaña sept. | C36: Sept. 1 al 23 | D36: Oct. 1 al 23
A37: CM vencidas | B37: 88 | C37: 64 | D37: 39
A38: CM realizadas | B38: 67 | C38: 50 | D38: 26
A39: Inscripciones | B39: 30 | C39: 26 | D39: 15
A40: Eficiencia de pauta | B40: Campaña sept. | D40: Octubre (4-23) | E40: Variación
A41: Gasto por día | B41: 155.55356 | D41: 167.8115 | E41: =D41/B41-1 -> 0.078802085
A42: Conversaciones por día | B42: 12.555556 | D42: 18.45 | E42: =D42/B42-1 -> 0.46946903
A43: Costo por conversación | B43: 12.39 | D43: 9.0954743 | E43: =D43/B43-1 -> -0.265902
A44: CM agendadas por día | B44: 2.0222222 | D44: 1.9655172 | E44: =D44/B44-1 -> -0.028040925
A45: Conversación → CM agendada | B45: 0.16106195 | D45: 0.1065321 | E45: =D45/B45-1 -> -0.33856444
A46: Costo por inscripción | B46: 304.34 | D46: 223.74867 | E46: =D46/B46-1 -> -0.2648069
A48: D. Embudo octubre
A49: CM vencidas | B49: =Datos!$B$4 -> 39
A50: Realizadas | B50: =Datos!$B$5 -> 26
A51: Inscritos | B51: =Datos!$B$7 -> 15
A53: E. Clases muestra por semana (prospectos nuevos)
A54: Semana (lunes) | B54: Inscritos | C54: Asistió sin inscribirse | D54: No asistió | E54: Cita agendada | F54: Total
A55: 28/09 | B55: 2 | C55: 1 | D55: 0 | E55: 0 | F55: =SUM(B55:E55) -> 3
A56: 05/10 | B56: 6 | C56: 2 | D56: 6 | E56: 0 | F56: =SUM(B56:E56) -> 14
A57: 12/10 | B57: 4 | C57: 5 | D57: 4 | E57: 0 | F57: =SUM(B57:E57) -> 13
A58: 19/10 | B58: 3 | C58: 3 | D58: 3 | E58: 7 | F58: =SUM(B58:E58) -> 16
A59: 26/10 | B59: 0 | C59: 0 | D59: 0 | E59: 11 | F59: =SUM(B59:E59) -> 11
A60: 02/11 | B60: 0 | C60: 0 | D60: 0 | E60: 2 | F60: =SUM(B60:E60) -> 2
A62: F. Por canal de origen (CM vencidas octubre)
A63: Canal | B63: CM vencidas | C63: Realizadas | D63: Inscritos | E63: Cierre
A64: Facebook | B64: 20 | C64: 16 | D64: 13 | E64: =IF(C64=0,"",D64/C64) -> 0.8125
A65: WhatsApp | B65: 14 | C65: 8 | D65: 2 | E65: =IF(C65=0,"",D65/C65) -> 0.25
A66: Instagram | B66: 5 | C66: 2 | D66: 0 | E66: =IF(C66=0,"",D66/C66) -> 0
A68: G. Por programa (CM vencidas octubre)
A69: Programa | B69: CM vencidas | C69: Inasistencias | D69: Inscritos | E69: Asistencia | F69: CM → inscripción
A70: Kids, Junior y Parenthood | B70: 19 | C70: 4 | D70: 10 | E70: =(B70-C70)/B70 -> 0.78947368 | F70: =D70/B70 -> 0.52631579
A71: College (adultos) | B71: 20 | C71: 9 | D71: 5 | E71: =(B71-C71)/B71 -> 0.55 | F71: =D71/B71 -> 0.25
A73: H. Por horario de la CM (octubre)
A74: Horario | B74: CM vencidas | C74: Inasistencias | D74: Inscritos | E74: Inasistencia %
A75: L-V mañana (antes de 14 h) | B75: 8 | C75: 2 | D75: 3 | E75: =IF(B75=0,"",C75/B75) -> 0.25
A76: L-V tarde (14 a 18 h) | B76: 20 | C76: 6 | D76: 9 | E76: =IF(B76=0,"",C76/B76) -> 0.3
A77: L-V noche (18 h o más) | B77: 10 | C77: 5 | D77: 2 | E77: =IF(B77=0,"",C77/B77) -> 0.5
A78: Sábado | B78: 1 | C78: 0 | D78: 1 | E78: =IF(B78=0,"",C78/B78) -> 0
A80: I. Motivos de no inscripción (asistieron sin inscribirse)
A81: Motivo | B81: Octubre | C81: Septiembre (mes)
A82: Horarios | B82: 4 | C82: 6
A83: Sin respuesta | B83: 2 | C83: 9
A84: Pendiente de decisión | B84: 2 | C84: 4
A85: Inscripción pospuesta | B85: 2 | C85: 0
A86: Ubicación | B86: 0 | C86: 6
A87: Precio | B87: 0 | C87: 3
A88: Motivos personales | B88: 0 | C88: 2
A89: Sin motivo registrado | B89: 1 | C89: 0
A91: J. Gasto por anuncio (4 al 23-oct)
A92: Anuncio | B92: Gasto | C92: Conversaciones | D92: Costo por conversación | E92: % del gasto
A93: Eres de Pachuca | B93: 2944.19 | C93: 348 | D93: =IF(C93=0,"Sin resultados",B93/C93) -> 8.4603161 | E93: =B93/Datos!$B$19 -> 0.8772313
A94: Post octubre | B94: 222.78 | C94: 16 | D94: =IF(C94=0,"Sin resultados",B94/C94) -> 13.92375 | E94: =B94/Datos!$B$19 -> 0.066378049
A95: pierde el miedo | B95: 91.16 | C95: 3 | D95: =IF(C95=0,"Sin resultados",B95/C95) -> 30.386667 | E95: =B95/Datos!$B$19 -> 0.027161428
A96: Terror | B96: 73.35 | C96: 2 | D96: =IF(C96=0,"Sin resultados",B96/C96) -> 36.675 | E96: =B96/Datos!$B$19 -> 0.021854879
A97: Niña Nancy | B97: 19.26 | C97: 0 | D97: =IF(C97=0,"Sin resultados",B97/C97) -> Sin resultados | E97: =B97/Datos!$B$19 -> 0.0057385817
A98: porque elegir kugelman | B98: 5.49 | C98: 0 | D98: =IF(C98=0,"Sin resultados",B98/C98) -> Sin resultados | E98: =B98/Datos!$B$19 -> 0.0016357639
A100: K. Presupuesto de octubre
A101: Gastado al 23-oct | B101: 3356.23
A102: Proyección 24 al 31-oct | B102: =Datos!$B$24*8 -> 1342.492
A103: Margen frente a $5,000 | B103: =Datos!$B$22-B101-B102 -> 301.278
A105: L. Escenarios mensuales
A106: Escenario | B106: Presupuesto | C106: Conversaciones | D106: CM agendadas | E106: Inscripciones | F106: Costo por inscripción | G106: Supuestos
A107: A. $5,000 con el proceso actual | B107: 5000 | C107: 550 | D107: 58.6 | E107: 22.5 | F107: =B107/E107 -> 221.98223 | G107: Tasas reales de octubre al 23-oct.
A108: B. $5,000 con las tasas de la campaña de septiembre | B108: 5000 | C108: 550 | D108: 88.5 | E108: 31.1 | F108: =B108/E108 -> 160.54556 | G108: Costo por conversación de octubre; agendamiento, asistencia y cierre de la campaña de septiembre.
A109: C. $5,000 con las metas propuestas | B109: 5000 | C109: 550 | D109: 88 | E109: 36.3 | F109: =B109/E109 -> 137.81022 | G109: Recuperar el agendamiento de septiembre (16%), asistencia de 75% con confirmación registrada y cierre de 55%.
A110: D. $7,000 con el proceso actual | B110: 7000 | C110: 770 | D110: 82 | E110: 31.5 | F110: =B110/E110 -> 221.98223 | G110: Más pauta sin cambiar el proceso. Riesgo: en septiembre, a más volumen semanal, menor tasa de agendamiento; el costo por conversación podría subir.
A112: M. Propuesta de pauta noviembre
A113: Conjunto "Familias" (Kids, Junior, Parenthood) | B113: 2500 | G113: Mejor cierre (53% en octubre) y sin bajas tempranas. Mensaje: sábados y grupos con cupo.
...
