Workbook

Sheet Estrategias
A1: Plan de estrategias comerciales complementarias a redes sociales
A2: Ninguna acción está autorizada todavía: todas tienen estatus "Propuesta". Las metas son propuestas y no resultados garantizados. Presupuesto solo donde hay una base para calcularlo.
A4: ID | B4: Prioridad | C4: Estrategia | D4: Objetivo | E4: Público | F4: Actividad concreta | G4: Ubicación o tipo de aliado | H4: Inicio | I4: Fin | J4: Responsable | K4: Áreas que participan | L4: Materiales y recursos | M4: Presupuesto estimado | N4: Base del presupuesto | O4: Meta esperada | P4: Indicador de evaluación | Q4: Seguimiento para convertir | R4: Evidencia que la respalda | S4: Estatus
A5: E1 | B5: Alta | C5: Recuperar prospectos que ya asistieron o ya escribieron | D5: Convertir en inscripción a personas que ya mostraron interés y por las que ya se pagó pauta. | E5: 12 asistentes de octubre sin inscripción (11 del control y 1 de la encuesta), 20 citas agendadas al 7-nov, y prospectos "por cerrar" y "en descubrimiento" del CRM de septiembre (284 sin movimiento al 3-oct). | F5: Llamada o mensaje personal en 48 h a los 11 de octubre, con dos horarios concretos que tengan lugar. Para septiembre: mensaje de reactivación con fecha de clase muestra propuesta; 3 intentos máximo y luego "Perdido" con motivo. | G5: No aplica (atención comercial por WhatsApp y teléfono). | H5: 46319 | I5: 46332 | J5: Atención comercial | K5: Marketing-Comercial | L5: Lista de prospectos (sistema de seguimiento), guion de cierre, horarios con cupo (hoja Ocupacion). | M5: 0 | N5: Sin costo directo: tiempo del equipo de atención. | O5: Propuesta: 100% de los 12 de octubre contactados antes del 28-oct y con resultado registrado. | P5: Inscripciones recuperadas; % de prospectos con resultado registrado. | Q5: Quien no decide queda con siguiente acción a 7 días; quien dice no, con motivo de pérdida. | R5: Brisa Azul dijo en la encuesta que se inscribiría "hoy mismo" y al 23-oct sigue sin inscribirse; 11 asistentes del control y 1 de la encuesta siguen sin cierre. | S5: Propuesta
A6: E2 | B6: Alta | C6: Programa de recomendación de alumnos y padres | D6: Formalizar el canal que más alumnos activos trae después de Facebook, sin costo de pauta. | E6: 120 alumnos activos y sus familias; énfasis en Kids y Junior (mejor cierre y menor baja temprana). | F6: Mensaje y tarjeta con el nombre del alumno que recomienda. El recomendado toma clase muestra; si se inscribe y paga su segundo mes, quien recomendó recibe el beneficio. Registrar canal "Recomendación" y el nombre del alumno en "Anuncio / referidor". | G6: En la academia (recepción, salones) y por WhatsApp a tutores. | H6: 46335 | I6: 46465 | J6: Coordinación comercial | K6: Marketing-Comercial; Finanzas (beneficio); Publicidad-Diseño (tarjeta y mensaje); Docentes (invitación en clase) | L6: Tarjeta impresa o digital, mensaje para tutores, cartel en recepción, registro en el sistema. | M6: Por definir | N6: Beneficio propuesto: $200 de descuento por recomendado que paga su segundo mes (pendiente de Finanzas). Se paga solo por altas que se quedan, contra un costo de adquisición atribuible de $304 en septiembre. | O6: Propuesta: 5 inscripciones por recomendación al mes (histórico sin programa: ~3 al mes; 57 registros desde mayo de 2025). | P6: Recomendados registrados, clases muestra, inscritos, inscritos activos a 60 días, costo por inscripción. | Q6: Agradecer a quien recomienda en cuanto el referido agenda; confirmar la CM un día antes; check-in de semana 1 y 3 al nuevo alumno. | R6: Recomendación: 57 registros históricos y 27 activos (22% de los activos). | S6: Propuesta
A7: E3 | B7: Alta | C7: Alianzas con escuelas cercanas: taller de inglés y beneficio para familias | D7: Generar prospectos de Kids y Junior en escuelas que ya han enviado alumnos y presentar opciones de horario con cupo. | E7: Alumnos de primaria y secundaria y sus padres. Alumnos de secundaria del turno vespertino podrían llenar grupos matutinos (hipótesis a validar). | F7: Reunión con la dirección de cada escuela; taller de 50 min en la escuela o visita de un grupo a la academia; volante para padres con dos horarios con cupo y el número de WhatsApp. Registrar canal "Escuela / aliado" y el nombre de la escuela. | G7: Escuelas con antecedente: Activacion Escuela, Escuela Florinda Chapa, Escuela Tecnica 66, Alumno Iunhi, Escuela Cuauhtemoc, Stand Chitiva; y "Freinet" (15 registros "Recomendado Freinet": validar si es escuela). | H7: 46321 | I7: 46444 | J7: Coordinación comercial | K7: Marketing-Comercial; Dirección (convenios); Académico (taller); Publicidad-Diseño (volante) | L7: Presentación breve para directores, guion del taller, volante para padres, hoja de registro con teléfono. | M7: 200 | N7: Costo docente de una sesión de 50 min ($200) por taller. Impresión: por cotizar. | O7: Propuesta: 2 escuelas con taller antes del 11-dic y 2 más entre enero y febrero. | P7: Contactos con teléfono por escuela, clases muestra, inscritos, costo por inscrito. | Q7: Mensaje a los padres registrados en 24 h con dos horarios; confirmación de CM; llamada de cierre a la semana. | R7: Escuelas, activaciones y aliados: 23 registros y 10 activos. "Activación escuela" aportó 9 altas, todas activas hoy. | S7: Propuesta
A8: E4 | B8: Alta | C8: Recuperar bajas temporales y exalumnos para enero | D8: Reinscribir a alumnos que ya conocen la academia antes de buscar alumnos nuevos. | E8: Bajas temporales de octubre (Lianne Flores, Paula Rodríguez, Montserrat Lugo, María Cristina Carrillo), bajas por vacaciones y exalumnos inactivos con motivo distinto a "Preferí otra escuela". | F8: Llamada personal (no mensaje masivo) con propuesta de horario y fecha de regreso en enero. Registrar resultado en la hoja Bajas. | G8: No aplica (atención comercial). | H8: 46357 | I8: 46402 | J8: Atención comercial | K8: Marketing-Comercial; Administración (datos de contacto); Académico (nivel de regreso) | L8: Lista de bajas con motivo, guion de regreso, horarios con cupo. | M8: 0 | N8: Sin costo directo. | O8: Propuesta: contactar al 100% de las bajas temporales antes del 18-dic. | P8: Reinscritos; reinscritos activos a 30 días. | Q8: Quien no regresa en enero queda con seguimiento a 30 días y motivo actualizado. | R8: Registro de deserción: 4 bajas temporales, 0 retenidos y 0 reinscritos. En todos los casos el último contacto fue el día de la baja. | S8: Propuesta
A9: E5 | B9: Media | C9: Clase abierta de sábado para familias y recomendados | D9: Llenar lugares de sábado y de mañana con prospectos que llegan por recomendación, escuelas y calle. | E9: Familias invitadas por alumnos, padres contactados en escuelas, prospectos de la calle. | F9: Sesión demostrativa de 50 min por grupo de edad (niños / adolescentes y adultos). Al terminar: registro, propuesta de horario y clase muestra formal si hace falta. | G9: Instalaciones de la academia, Villas de Pachuca. | H9: 46347 | I9: 46459 | J9: Coordinación comercial | K9: Marketing-Comercial; Académico (docentes); Publicidad-Diseño (invitación) | L9: Invitación digital, lista de asistencia con teléfono, horarios con cupo impresos. | M9: 400 | N9: Costo docente: 2 sesiones de 50 min x $200 por evento. Fechas propuestas: 21-nov, 5-dic, 16-ene, 20-feb y 13-mar. | O9: Propuesta: definir después del primer evento con su resultado real. | P9: Asistentes, asistentes con teléfono, inscritos por evento, costo por inscrito. | Q9: Mensaje a cada asistente el mismo día con dos horarios; llamada de cierre a los 3 días. | R9: La clase muestra cierra 46-52% de quienes asisten. La ocupación de mañana es ~42%. | S9: Propuesta
A10: E6 | B10: Media | C10: Visibilidad física de la academia (tránsito) | D10: Convertir el paso frente a la academia en contactos registrados. | E10: Vecinos y personas que pasan frente a la academia en Villas de Pachuca. | F10: Letrero o lona con "Clase muestra gratis", WhatsApp, código QR y los horarios con cupo. Exhibidor con volantes en la entrada. Registrar canal "Tránsito". | G10: Fachada y entrada de la academia. | H10: 46328 | I10: 46346 | J10: Publicidad-Diseño | K10: Publicidad-Diseño (diseño); Dirección (autorización y compra); Marketing-Comercial (registro) | L10: Lona o letrero, exhibidor, volantes. | M10: Por definir | N10: Por cotizar: no hay referencias de precio en la información disponible. | O10: Propuesta: medir la línea base de noviembre y fijar meta en diciembre. | P10: Prospectos con canal "Tránsito" por mes; inscritos. | Q10: Mismo proceso del sistema de seguimiento. | R10: Tránsito: 40 registros históricos y 16 activos. | S10: Propuesta
A11: E7 | B11: Media | C11: Promoción en calle con registro de contactos | D11: Mantener la promoción en calle, pero midiendo lo que produce. | E11: Padres a la salida de escuelas cercanas y residentes de Villas de Pachuca y colonias vecinas. | F11: Dos tardes por semana a la salida de escuelas. Volante con horarios, precio de lista y el beneficio principal; registro de teléfono en el momento (formulario o QR). Canal "Promoción en calle" y el lugar en "Anuncio / referidor / lugar". | G11: Salidas de escuelas cercanas y zonas comerciales de Villas de Pachuca (lugares a definir por el equipo). | H11: 46329 | I11: 46465 | J11: Atención comercial | K11: Marketing-Comercial; Publicidad-Diseño (volante) | L11: Volantes, formulario o QR para registro, playera o gafete de la academia. | M11: Por definir | N11: Volantes por cotizar; tiempo del personal. | O11: Propuesta: al menos 10 contactos con teléfono por salida. | P11: Contactos con teléfono por salida, CM, inscritos, costo por inscrito. | Q11: Mensaje en 24 h a cada contacto con dos horarios. Atender las barreras que ya mencionaron: horario, precio y ubicación. | R11: Los hermanos Villalba dijeron en la encuesta que llegaron por promoción en calle (en el control aparecen como WhatsApp) y señalaron horarios, inversión y ubicación como barreras. | S11: Propuesta
A12: E8 | B12: Media | C12: Curso intensivo de invierno (evaluar) | D12: Usar la capacidad de la mañana durante las vacaciones escolares y convertir a alumnos regulares en enero. | E12: Niños y adolescentes en vacaciones (21-dic a 6-ene). | F12: Curso corto de mañana; al cierre, clase de presentación del programa regular con horarios de enero. | G12: Instalaciones de la academia. | H12: 46377 | I12: 46393 | J12: Dirección | K12: Dirección; Académico; Finanzas (precio); Marketing-Comercial (venta) | L12: Programa del curso, docentes disponibles, precio aprobado. | M12: Por definir | N12: Costo docente: $200 por sesión de 50 min. Número de sesiones y precio: definir con Académico y Finanzas. | O12: Propuesta: decidir antes del 20-nov si se realiza. | P12: Inscritos al curso; % que se inscribe al programa regular en enero. | Q12: Clase de presentación del programa regular el último día; llamada a cada familia antes del 11-ene. | R12: Hubo curso de verano (5 registros en la base). La ocupación de la mañana es ~42%. No hay datos de demanda en invierno: es una prueba. | S12: Propuesta
A13: E9 | B13: Baja | C13: Convenios con empresas e instituciones cercanas | D13: Atraer adultos a horarios de mañana y noche, donde hay lugares libres. | E13: Empleados de negocios, clínicas y oficinas de la zona; estudiantes universitarios (antecedente IUNHI). | F13: Visita con propuesta de beneficio para empleados (a definir con Finanzas) y clase muestra en grupo. Registro con canal "Escuela / aliado" y el nombre de la empresa. | G13: Empresas e instituciones de Villas de Pachuca y zonas cercanas (lista a construir). | H13: 46398 | I13: 46465 | J13: Coordinación comercial | K13: Marketing-Comercial; Dirección (convenio); Finanzas (beneficio) | L13: Presentación de una página, propuesta de convenio. | M13: Por definir | N13: Depende del beneficio que apruebe Finanzas. | O13: Propuesta: 2 convenios firmados en el trimestre. | P13: Convenios, prospectos, inscritos y activos a 60 días por convenio. | Q13: Check-in en semana 1 y 3 (los adultos tienen la mayor baja temprana). | R13: Prioridad baja a propósito: College cierra menos y en octubre concentró las 4 bajas tempranas. Primero hay que corregir la retención de adultos. | S13: Propuesta
A14: E10 | B14: Baja | C14: Segundo idioma y hermanos para familias actuales | D14: Subir el ingreso por familia con alumnos que ya confían en la academia. | E14: Familias activas; alumnos de inglés interesados en francés. | F14: Clase muestra de francés mensual para alumnos actuales, con confirmación; mensaje a familias con hijos aún no inscritos. | G14: Instalaciones de la academia. | H14: 46398 | I14: 46465 | J14: Coordinación comercial | K14: Marketing-Comercial; Académico; Finanzas (descuento de hermanos) | L14: Mensaje a tutores, horario de francés con cupo. | M14: 0 | N14: Sin costo adicional si se usa un grupo existente con lugar (Francés 1 tiene 6 alumnos). | O14: Propuesta: definir con el resultado de enero. | P14: Inscripciones de segundo idioma o hermanos. | Q14: Confirmar la CM; en octubre las 3 alumnas que pidieron muestra de francés no asistieron. | R14: En septiembre, 3 inscripciones de francés vinieron de alumnos existentes. | S14: Propuesta

Sheet Eventos
A1: Eventos y actividades con fecha
A2: Una fila por actividad. El calendario marca con ● la semana de cada evento. Las columnas de resultados se llenan después de cada evento.
A4: ID estrategia | B4: Fecha | C4: Actividad | D4: Lugar / aliado | E4: Responsable | F4: Estatus | G4: Contactos | H4: Contactos con teléfono | I4: CM agendadas | J4: CM realizadas | K4: Inscritos | L4: Costo real | M4: Costo por inscrito | N4: Notas
A5: E1 | B5: 46319 | C5: Llamadas de cierre a los 12 asistentes de octubre sin inscripción | D5: Academia | E5: Atención comercial | F5: Propuesta | M5: =IF(OR(K5="",K5=0),"",L5/K5)
A6: E1 | B6: 46322 | C6: Reactivación de prospectos "por cerrar" de septiembre | D6: Academia | E6: Atención comercial | F6: Propuesta | M6: =IF(OR(K6="",K6=0),"",L6/K6)
A7: E3 | B7: 46323 | C7: Contacto con direcciones de escuelas con antecedente | D7: Escuelas con antecedente | E7: Coordinación comercial | F7: Propuesta | M7: =IF(OR(K7="",K7=0),"",L7/K7)
A8: E6 | B8: 46328 | C8: Diseño y cotización de lona/letrero con horarios con cupo | D8: Fachada | E8: Publicidad-Diseño | F8: Propuesta | M8: =IF(OR(K8="",K8=0),"",L8/K8)
A9: E7 | B9: 46330 | C9: Primera salida de promoción en calle con registro | D9: Por definir | E9: Atención comercial | F9: Propuesta | M9: =IF(OR(K9="",K9=0),"",L9/K9)
A10: E2 | B10: 46335 | C10: Lanzamiento del programa de recomendación (mensaje a tutores) | D10: Academia / WhatsApp | E10: Coordinación comercial | F10: Propuesta | M10: =IF(OR(K10="",K10=0),"",L10/K10)
A11: E3 | B11: 46344 | C11: Taller en escuela 1 | D11: Por confirmar | E11: Coordinación comercial | F11: Propuesta | M11: =IF(OR(K11="",K11=0),"",L11/K11)
A12: E8 | B12: 46346 | C12: Decisión sobre curso de invierno | D12: Dirección | E12: Dirección | F12: Propuesta | M12: =IF(OR(K12="",K12=0),"",L12/K12)
A13: E5 | B13: 46347 | C13: Clase abierta de sábado | D13: Academia | E13: Coordinación comercial | F13: Propuesta | M13: =IF(OR(K13="",K13=0),"",L13/K13)
A14: E4 | B14: 46357 | C14: Inicio de llamadas a bajas temporales y exalumnos | D14: Academia | E14: Atención comercial | F14: Propuesta | M14: =IF(OR(K14="",K14=0),"",L14/K14)
A15: E5 | B15: 46361 | C15: Clase abierta de sábado | D15: Academia | E15: Coordinación comercial | F15: Propuesta | M15: =IF(OR(K15="",K15=0),"",L15/K15)
A16: E3 | B16: 46365 | C16: Taller en escuela 2 | D16: Por confirmar | E16: Coordinación comercial | F16: Propuesta | M16: =IF(OR(K16="",K16=0),"",L16/K16)
... A24: E5 | B24: 46459 | C24: Clase abierta de sábado | D24: Academia | E24: Coordinación comercial | F24: Propuesta | M24: =IF(OR(K24="",K24=0),"",L24/K24)
M25: =IF(OR(K25="",K25=0),"",L25/K25)
M26: =IF(OR(K26="",K26=0),"",L26/K26)
M27: =IF(OR(K27="",K27=0),"",L27/K27)
M28: =IF(OR(K28="",K28=0),"",L28/K28)
M29: =IF(OR(K29="",K29=0),"",L29/K29)
M30: =IF(OR(K30="",K30=0),"",L30/K30)
M31: =IF(OR(K31="",K31=0),"",L31/K31)
M32: =IF(OR(K32="",K32=0),"",L32/K32)
M33: =IF(OR(K33="",K33=0),"",L33/K33)
M34: =IF(OR(K34="",K34=0),"",L34/K34)
M35: =IF(OR(K35="",K35=0),"",L35/K35)
M36: =IF(OR(K36="",K36=0),"",L36/K36)
... M154: =IF(OR(K154="",K154=0),"",L154/K154)

Sheet Calendario
A1: Calendario comercial · semana del 19-oct-2026 a marzo de 2027 (actualizado al 23-oct)
A2: ■ = estrategia en curso (según fechas de la hoja Estrategias) · ● = semana con evento (hoja Eventos). Cambiar fechas en esas hojas actualiza el calendario.
A4: ID | B4: Estrategia | C4: Prioridad | D4: oct | F4: nov | K4: dic | O4: ene | S4: feb | W4: mar
B5: Semana que inicia (lunes) | D5: 46314 | E5: 46321 | F5: 46328 | G5: 46335 | H5: 46342 | I5: 46349 | J5: 46356 | K5: 46363 | L5: 46370 | M5: 46377 | N5: 46384 | O5: 46391 | P5: 46398 | Q5: 46405 | R5: 46412 | S5: 46419 | T5: 46426 | U5: 46433 | V5: 46440 | W5: 46447 | X5: 46454 | Y5: 46461 | Z5: 46468 | AA5: 46475
B6: Fechas clave
B7: Fin de campaña Meta de octubre | D7: =IF(AND(D$5<=$AE7,D$5+6>=$AD7),"◆","") | E7: =IF(AND(E$5<=$AE7,E$5+6>=$AD7),"◆","") | F7: =IF(AND(F$5<=$AE7,F$5+6>=$AD7),"◆","") -> ◆ | G7: =IF(AND(G$5<=$AE7,G$5+6>=$AD7),"◆","") | H7: =IF(AND(H$5<=$AE7,H$5+6>=$AD7),"◆","") | I7: =IF(AND(I$5<=$AE7,I$5+6>=$AD7),"◆","") | J7: =IF(AND(J$5<=$AE7,J$5+6>=$AD7),"◆","") | K7: =IF(AND(K$5<=$AE7,K$5+6>=$AD7),"◆","") | ... AA7: =IF(AND(AA$5<=$AE7,AA$5+6>=$AD7),"◆","") | AD7: 46328 | AE7: 46328
B8: Buen Fin | D8: =IF(AND(D$5<=$AE8,D$5+6>=$AD8),"◆","") | E8: =IF(AND(E$5<=$AE8,E$5+6>=$AD8),"◆","") | F8: =IF(AND(F$5<=$AE8,F$5+6>=$AD8),"◆","") | G8: =IF(AND(G$5<=$AE8,G$5+6>=$AD8),"◆","") -> ◆ | H8: =IF(AND(H$5<=$AE8,H$5+6>=$AD8),"◆","") -> ◆ | I8: =IF(AND(I$5<=$AE8,I$5+6>=$AD8),"◆","") | J8: =IF(AND(J$5<=$AE8,J$5+6>=$AD8),"◆","") | K8: =IF(AND(K$5<=$AE8,K$5+6>=$AD8),"◆","") | ... AA8: =IF(AND(AA$5<=$AE8,AA$5+6>=$AD8),"◆","") | AD8: 46339 | AE8: 46343
B9: Asueto (Revolución) | D9: =IF(AND(D$5<=$AE9,D$5+6>=$AD9),"◆","") | E9: =IF(AND(E$5<=$AE9,E$5+6>=$AD9),"◆","") | F9: =IF(AND(F$5<=$AE9,F$5+6>=$AD9),"◆","") | G9: =IF(AND(G$5<=$AE9,G$5+6>=$AD9),"◆","") | H9: =IF(AND(H$5<=$AE9,H$5+6>=$AD9),"◆","") -> ◆ | I9: =IF(AND(I$5<=$AE9,I$5+6>=$AD9),"◆","") | J9: =IF(AND(J$5<=$AE9,J$5+6>=$AD9),"◆","") | K9: =IF(AND(K$5<=$AE9,K$5+6>=$AD9),"◆","") | ... AA9: =IF(AND(AA$5<=$AE9,AA$5+6>=$AD9),"◆","") | AD9: 46342 | AE9: 46342
B10: Vacaciones SEP de invierno | D10: =IF(AND(D$5<=$AE10,D$5+6>=$AD10),"◆","") | E10: =IF(AND(E$5<=$AE10,E$5+6>=$AD10),"◆","") | F10: =IF(AND(F$5<=$AE10,F$5+6>=$AD10),"◆","") | G10: =IF(AND(G$5<=$AE10,G$5+6>=$AD10),"◆","") | H10: =IF(AND(H$5<=$AE10,H$5+6>=$AD10),"◆","") | I10: =IF(AND(I$5<=$AE10,I$5+6>=$AD10),"◆","") | J10: =IF(AND(J$5<=$AE10,J$5+6>=$AD10),"◆","") | K10: =IF(AND(K$5<=$AE10,K$5+6>=$AD10),"◆","") | ... AA10: =IF(AND(AA$5<=$AE10,AA$5+6>=$AD10),"◆","") | AD10: 46377 | AE10: 46393
B11: Asueto (Constitución) | D11: =IF(AND(D$5<=$AE11,D$5+6>=$AD11),"◆","") | E11: =IF(AND(E$5<=$AE11,E$5+6>=$AD11),"◆","") | F11: =IF(AND(F$5<=$AE11,F$5+6>=$AD11),"◆","") | G11: =IF(AND(G$5<=$AE11,G$5+6>=$AD11),"◆","") | H11: =IF(AND(H$5<=$AE11,H$5+6>=$AD11),"◆","") | I11: =IF(AND(I$5<=$AE11,I$5+6>=$AD11),"◆","") | J11: =IF(AND(J$5<=$AE11,J$5+6>=$AD11),"◆","") | K11: =IF(AND(K$5<=$AE11,K$5+6>=$AD11),"◆","") | ... AA11: =IF(AND(AA$5<=$AE11,AA$5+6>=$AD11),"◆","") | AD11: 46419 | AE11: 46419
B12: Asueto (Natalicio de Benito Juárez) | D12: =IF(AND(D$5<=$AE12,D$5+6>=$AD12),"◆","") | E12: =IF(AND(E$5<=$AE12,E$5+6>=$AD12),"◆","") | F12: =IF(AND(F$5<=$AE12,F$5+6>=$AD12),"◆","") | G12: =IF(AND(G$5<=$AE12,G$5+6>=$AD12),"◆","") | H12: =IF(AND(H$5<=$AE12,H$5+6>=$AD12),"◆","") | I12: =IF(AND(I$5<=$AE12,I$5+6>=$AD12),"◆","") | J12: =IF(AND(J$5<=$AE12,J$5+6>=$AD12),"◆","") | K12: =IF(AND(K$5<=$AE12,K$5+6>=$AD12),"◆","") | ... AA12: =IF(AND(AA$5<=$AE12,AA$5+6>=$AD12),"◆","") | AD12: 46461 | AE12: 46461
B13: Vacaciones SEP de Semana Santa | D13: =IF(AND(D$5<=$AE13,D$5+6>=$AD13),"◆","") | E13: =IF(AND(E$5<=$AE13,E$5+6>=$AD13),"◆","") | F13: =IF(AND(F$5<=$AE13,F$5+6>=$AD13),"◆","") | G13: =IF(AND(G$5<=$AE13,G$5+6>=$AD13),"◆","") | H13: =IF(AND(H$5<=$AE13,H$5+6>=$AD13),"◆","") | I13: =IF(AND(I$5<=$AE13,I$5+6>=$AD13),"◆","") | J13: =IF(AND(J$5<=$AE13,J$5+6>=$AD13),"◆","") | K13: =IF(AND(K$5<=$AE13,K$5+6>=$AD13),"◆","") | ... AA13: =IF(AND(AA$5<=$AE13,AA$5+6>=$AD13),"◆","") -> ◆ | AD13: 46468 | AE13: 46479
B15: Estrategias
A16: =Estrategias!A5 -> E1 | B16: =Estrategias!C5 -> Recuperar prospectos que ya asistieron o ya escribieron | C16: =Estrategias!B5 -> Alta | D16: =IF(COUNTIFS(Eventos!$A$5:$A$154,$A16,Eventos!$B$5:$B$154,">="&D$5,Eventos!$B$5:$B$154,"<="&D$5+6)>0,"●",IF(AND(D$5<=Estrategias!$I$5,D$5+6>=Estrategias!$H$5),"■","")) -> ● | E16: =IF(COUNTIFS(Eventos!$A$5:$A$154,$A16,Eventos!$B$5:$B$154,">="&E$5,Eventos!$B$5:$B$154,"<="&E$5+6)>0,"●",IF(AND(E$5<=Estrategias!$I$5,E$5+6>=Estrategias!$H$5),"■","")) -> ● | F16: =IF(COUNTIFS(Eventos!$A$5:$A$154,$A16,Eventos!$B$5:$B$154,">="&F$5,Eventos!$B$5:$B$154,"<="&F$5+6)>0,"●",IF(AND(F$5<=Estrategias!$I$5,F$5+6>=Estrategias!$H$5),"■","")) -> ■ | G16: =IF(COUNTIFS(Eventos!$A$5:$A$154,$A16,Eventos!$B$5:$B$154,">="&G$5,Eventos!$B$5:$B$154,"<="&G$5+6)>0,"●",IF(AND(G$5<=Estrategias!$I$5,G$5+6>=Estrategias!$H$5),"■","")) | H16: =IF(COUNTIFS(Eventos!$A$5:$A$154,$A16,Eventos!$B$5:$B$154,">="&H$5,Eventos!$B$5:$B$154,"<="&H$5+6)>0,"●",IF(AND(H$5<=Estrategias!$I$5,H$5+6>=Estrategias!$H$5),"■","")) | I16: =IF(COUNTIFS(Eventos!$A$5:$A$154,$A16,Eventos!$B$5:$B$154,">="&I$5,Eventos!$B$5:$B$154,"<="&I$5+6)>0,"●",IF(AND(I$5<=Estrategias!$I$5,I$5+6>=Estrategias!$H$5),"■","")) | J16: =IF(COUNTIFS(Eventos!$A$5:$A$154,$A16,Eventos!$B$5:$B$154,">="&J$5,Eventos!$B$5:$B$154,"<="&J$5+6)>0,"●",IF(AND(J$5<=Estrategias!$I$5,J$5+6>=Estrategias!$H$5),"■","")) | K16: =IF(COUNTIFS(Eventos!$A$5:$A$154,$A16,Eventos!$B$5:$B$154,">="&K$5,Eventos!$B$5:$B$154,"<="&K$5+6)>0,"●",IF(AND(K$5<=Estrategias!$I$5,K$5+6>=Estrategias!$H$5),"■","")) | ... AA16: =IF(COUNTIFS(Eventos!$A$5:$A$154,$A16,Eventos!$B$5:$B$154,">="&AA$5,Eventos!$B$5:$B$154,"<="&AA$5+6)>0,"●",IF(AND(AA$5<=Estrategias!$I$5,AA$5+6>=Estrategias!$H$5),"■",""))
A17: =Estrategias!A6 -> E2 | B17: =Estrategias!C6 -> Programa de recomendación de alumnos y padres | C17: =Estrategias!B6 -> Alta | D17: =IF(COUNTIFS(Eventos!$A$5:$A$154,$A17,Eventos!$B$5:$B$154,">="&D$5,Eventos!$B$5:$B$154,"<="&D$5+6)>0,"●",IF(AND(D$5<=Estrategias!$I$6,D$5+6>=Estrategias!$H$6),"■","")) | E17: =IF(COUNTIFS(Eventos!$A$5:$A$154,$A17,Eventos!$B$5:$B$154,">="&E$5,Eventos!$B$5:$B$154,"<="&E$5+6)>0,"●",IF(AND(E$5<=Estrategias!$I$6,E$5+6>=Estrategias!$H$6),"■","")) | F17: =IF(COUNTIFS(Eventos!$A$5:$A$154,$A17,Eventos!$B$5:$B$154,">="&F$5,Eventos!$B$5:$B$154,"<="&F$5+6)>0,"●",IF(AND(F$5<=Estrategias!$I$6,F$5+6>=Estrategias!$H$6),"■","")) | G17: =IF(COUNTIFS(Eventos!$A$5:$A$154,$A17,Eventos!$B$5:$B$154,">="&G$5,Eventos!$B$5:$B$154,"<="&G$5+6)>0,"●",IF(AND(G$5<=Estrategias!$I$6,G$5+6>=Estrategias!$H$6),"■","")) -> ● | H17: =IF(COUNTIFS(Eventos!$A$5:$A$154,$A17,Eventos!$B$5:$B$154,">="&H$5,Eventos!$B$5:$B$154,"<="&H$5+6)>0,"●",IF(AND(H$5<=Estrategias!$I$6,H$5+6>=Estrategias!$H$6),"■","")) -> ■ | I17: =IF(COUNTIFS(Eventos!$A$5:$A$154,$A17,Eventos!$B$5:$B$154,">="&I$5,Eventos!$B$5:$B$154,"<="&I$5+6)>0,"●",IF(AND(I$5<=Estrategias!$I$6,I$5+6>=Estrategias!$H$6),"■","")) -> ■ | J17: =IF(COUNTIFS(Eventos!$A$5:$A$154,$A17,Eventos!$B$5:$B$154,">="&J$5,Eventos!$B$5:$B$154,"<="&J$5+6)>0,"●",IF(AND(J$5<=Estrategias!$I$6,J$5+6>=Estrategias!$H$6),"■","")) -> ■ | K17: =IF(COUNTIFS(Eventos!$A$5:$A$154,$A17,Eventos!$B$5:$B$154,">="&K$5,Eventos!$B$5:$B$154,"<="&K$5+6)>0,"●",IF(AND(K$5<=Estrategias!$I$6,K$5+6>=Estrategias!$H$6),"■","")) -> ■ | ... AA17: =IF(COUNTIFS(Eventos!$A$5:$A$154,$A17,Eventos!$B$5:$B$154,">="&AA$5,Eventos!$B$5:$B$154,"<="&AA$5+6)>0,"●",IF(AND(AA$5<=Estrategias!$I$6,AA$5+6>=Estrategias!$H$6),"■",""))
A18: =Estrategias!A7 -> E3 | B18: =Estrategias!C7 -> Alianzas con escuelas cercanas: taller de inglés y beneficio para familias | C18: =Estrategias!B7 -> Alta | D18: =IF(COUNTIFS(Eventos!$A$5:$A$154,$A18,Eventos!$B$5:$B$154,">="&D$5,Eventos!$B$5:$B$154,"<="&D$5+6)>0,"●",IF(AND(D$5<=Estrategias!$I$7,D$5+6>=Estrategias!$H$7),"■","")) | E18: =IF(COUNTIFS(Eventos!$A$5:$A$154,$A18,Eventos!$B$5:$B$154,">="&E$5,Eventos!$B$5:$B$154,"<="&E$5+6)>0,"●",IF(AND(E$5<=Estrategias!$I$7,E$5+6>=Estrategias!$H$7),"■","")) -> ● | F18: =IF(COUNTIFS(Eventos!$A$5:$A$154,$A18,Eventos!$B$5:$B$154,">="&F$5,Eventos!$B$5:$B$154,"<="&F$5+6)>0,"●",IF(AND(F$5<=Estrategias!$I$7,F$5+6>=Estrategias!$H$7),"■","")) -> ■ | G18: =IF(COUNTIFS(Eventos!$A$5:$A$154,$A18,Eventos!$B$5:$B$154,">="&G$5,Eventos!$B$5:$B$154,"<="&G$5+6)>0,"●",IF(AND(G$5<=Estrategias!$I$7,G$5+6>=Estrategias!$H$7),"■","")) -> ■ | H18: =IF(COUNTIFS(Eventos!$A$5:$A$154,$A18,Eventos!$B$5:$B$154,">="&H$5,Eventos!$B$5:$B$154,"<="&H$5+6)>0,"●",IF(AND(H$5<=Estrategias!$I$7,H$5+6>=Estrategias!$H$7),"■","")) -> ● | I18: =IF(COUNTIFS(Eventos!$A$5:$A$154,$A18,Eventos!$B$5:$B$154,">="&I$5,Eventos!$B$5:$B$154,"<="&I$5+6)>0,"●",IF(AND(I$5<=Estrategias!$I$7,I$5+6>=Estrategias!$H$7),"■","")) -> ■ | J18: =IF(COUNTIFS(Eventos!$A$5:$A$154,$A18,Eventos!$B$5:$B$154,">="&J$5,Eventos!$B$5:$B$154,"<="&J$5+6)>0,"●",IF(AND(J$5<=Estrategias!$I$7,J$5+6>=Estrategias!$H$7),"■","")) -> ■ | K18: =IF(COUNTIFS(Eventos!$A$5:$A$154,$A18,Eventos!$B$5:$B$154,">="&K$5,Eventos!$B$5:$B$154,"<="&K$5+6)>0,"●",IF(AND(K$5<=Estrategias!$I$7,K$5+6>=Estrategias!$H$7),"■","")) -> ● | ... AA18: =IF(COUNTIFS(Eventos!$A$5:$A$154,$A18,Eventos!$B$5:$B$154,">="&AA$5,Eventos!$B$5:$B$154,"<="&AA$5+6)>0,"●",IF(AND(AA$5<=Estrategias!$I$7,AA$5+6>=Estrategias!$H$7),"■",""))
A19: =Estrategias!A8 -> E4 | B19: =Estrategias!C8 -> Recuperar bajas temporales y exalumnos para enero | C19: =Estrategias!B8 -> Alta | D19: =IF(COUNTIFS(Eventos!$A$5:$A$154,$A19,Eventos!$B$5:$B$154,">="&D$5,Eventos!$B$5:$B$154,"<="&D$5+6)>0,"●",IF(AND(D$5<=Estrategias!$I$8,D$5+6>=Estrategias!$H$8),"■","")) | E19: =IF(COUNTIFS(Eventos!$A$5:$A$154,$A19,Eventos!$B$5:$B$154,">="&E$5,Eventos!$B$5:$B$154,"<="&E$5+6)>0,"●",IF(AND(E$5<=Estrategias!$I$8,E$5+6>=Estrategias!$H$8),"■","")) | F19: =IF(COUNTIFS(Eventos!$A$5:$A$154,$A19,Eventos!$B$5:$B$154,">="&F$5,Eventos!$B$5:$B$154,"<="&F$5+6)>0,"●",IF(AND(F$5<=Estrategias!$I$8,F$5+6>=Estrategias!$H$8),"■","")) | G19: =IF(COUNTIFS(Eventos!$A$5:$A$154,$A19,Eventos!$B$5:$B$154,">="&G$5,Eventos!$B$5:$B$154,"<="&G$5+6)>0,"●",IF(AND(G$5<=Estrategias!$I$8,G$5+6>=Estrategias!$H$8),"■","")) | H19: =IF(COUNTIFS(Eventos!$A$5:$A$154,$A19,Eventos!$B$5:$B$154,">="&H$5,Eventos!$B$5:$B$154,"<="&H$5+6)>0,"●",IF(AND(H$5<=Estrategias!$I$8,H$5+6>=Estrategias!$H$8),"■","")) | I19: =IF(COUNTIFS(Eventos!$A$5:$A$154,$A19,Eventos!$B$5:$B$154,">="&I$5,Eventos!$B$5:$B$154,"<="&I$5+6)>0,"●",IF(AND(I$5<=Estrategias!$I$8,I$5+6>=Estrategias!$H$8),"■","")) | J19: =IF(COUNTIFS(Eventos!$A$5:$A$154,$A19,Eventos!$B$5:$B$154,">="&J$5,Eventos!$B$5:$B$154,"<="&J$5+6)>0,"●",IF(AND(J$5<=Estrategias!$I$8,J$5+6>=Estrategias!$H$8),"■","")) -> ● | K19: =IF(COUNTIFS(Eventos!$A$5:$A$154,$A19,Eventos!$B$5:$B$154,">="&K$5,Eventos!$B$5:$B$154,"<="&K$5+6)>0,"●",IF(AND(K$5<=Estrategias!$I$8,K$5+6>=Estrategias!$H$8),"■","")) -> ■ | ... AA19: =IF(COUNTIFS(Eventos!$A$5:$A$154,$A19,Eventos!$B$5:$B$154,">="&AA$5,Eventos!$B$5:$B$154,"<="&AA$5+6)>0,"●",IF(AND(AA$5<=Estrategias!$I$8,AA$5+6>=Estrategias!$H$8),"■",""))
A20: =Estrategias!A9 -> E5 | B20: =Estrategias!C9 -> Clase abierta de sábado para familias y recomendados | C20: =Estrategias!B9 -> Media | D20: =IF(COUNTIFS(Eventos!$A$5:$A$154,$A20,Eventos!$B$5:$B$154,">="&D$5,Eventos!$B$5:$B$154,"<="&D$5+6)>0,"●",IF(AND(D$5<=Estrategias!$I$9,D$5+6>=Estrategias!$H$9),"■","")) | E20: =IF(COUNTIFS(Eventos!$A$5:$A$154,$A20,Eventos!$B$5:$B$154,">="&E$5,Eventos!$B$5:$B$154,"<="&E$5+6)>0,"●",IF(AND(E$5<=Estrategias!$I$9,E$5+6>=Estrategias!$H$9),"■","")) | F20: =IF(COUNTIFS(Eventos!$A$5:$A$154,$A20,Eventos!$B$5:$B$154,">="&F$5,Eventos!$B$5:$B$154,"<="&F$5+6)>0,"●",IF(AND(F$5<=Estrategias!$I$9,F$5+6>=Estrategias!$H$9),"■","")) | G20: =IF(COUNTIFS(Eventos!$A$5:$A$154,$A20,Eventos!$B$5:$B$154,">="&G$5,Eventos!$B$5:$B$154,"<="&G$5+6)>0,"●",IF(AND(G$5<=Estrategias!$I$9,G$5+6>=Estrategias!$H$9),"■","")) | H20: =IF(COUNTIFS(Eventos!$A$5:$A$154,$A20,Eventos!$B$5:$B$154,">="&H$5,Eventos!$B$5:$B$154,"<="&H$5+6)>0,"●",IF(AND(H$5<=Estrategias!$I$9,H$5+6>=Estrategias!$H$9),"■","")) -> ● | I20: =IF(COUNTIFS(Eventos!$A$5:$A$154,$A20,Eventos!$B$5:$B$154,">="&I$5,Eventos!$B$5:$B$154,"<="&I$5+6)>0,"●",IF(AND(I$5<=Estrategias!$I$9,I$5+6>=Estrategias!$H$9),"■","")) -> ■ | J20: =IF(COUNTIFS(Eventos!$A$5:$A$154,$A20,Eventos!$B$5:$B$154,">="&J$5,Eventos!$B$5:$B$154,"<="&J$5+6)>0,"●",IF(AND(J$5<=Estrategias!$I$9,J$5+6>=Estrategias!$H$9),"■","")) -> ● | K20: =IF(COUNTIFS(Eventos!$A$5:$A$154,$A20,Eventos!$B$5:$B$154,">="&K$5,Eventos!$B$5:$B$154,"<="&K$5+6)>0,"●",IF(AND(K$5<=Estrategias!$I$9,K$5+6>=Estrategias!$H$9),"■","")) -> ■ | ... AA20: =IF(COUNTIFS(Eventos!$A$5:$A$154,$A20,Eventos!$B$5:$B$154,">="&AA$5,Eventos!$B$5:$B$154,"<="&AA$5+6)>0,"●",IF(AND(AA$5<=Estrategias!$I$9,AA$5+6>=Estrategias!$H$9),"■",""))
A21: =Estrategias!A10 -> E6 | B21: =Estrategias!C10 -> Visibilidad física de la academia (tránsito) | C21: =Estrategias!B10 -> Media | D21: =IF(COUNTIFS(Eventos!$A$5:$A$154,$A21,Eventos!$B$5:$B$154,">="&D$5,Eventos!$B$5:$B$154,"<="&D$5+6)>0,"●",IF(AND(D$5<=Estrategias!$I$10,D$5+6>=Estrategias!$H$10),"■","")) | E21: =IF(COUNTIFS(Eventos!$A$5:$A$154,$A21,Eventos!$B$5:$B$154,">="&E$5,Eventos!$B$5:$B$154,"<="&E$5+6)>0,"●",IF(AND(E$5<=Estrategias!$I$10,E$5+6>=Estrategias!$H$10),"■","")) | F21: =IF(COUNTIFS(Eventos!$A$5:$A$154,$A21,Eventos!$B$5:$B$154,">="&F$5,Eventos!$B$5:$B$154,"<="&F$5+6)>0,"●",IF(AND(F$5<=Estrategias!$I$10,F$5+6>=Estrategias!$H$10),"■","")) -> ● | G21: =IF(COUNTIFS(Eventos!$A$5:$A$154,$A21,Eventos!$B$5:$B$154,">="&G$5,Eventos!$B$5:$B$154,"<="&G$5+6)>0,"●",IF(AND(G$5<=Estrategias!$I$10,G$5+6>=Estrategias!$H$10),"■","")) -> ■ | H21: =IF(COUNTIFS(Eventos!$A$5:$A$154,$A21,Eventos!$B$5:$B$154,">="&H$5,Eventos!$B$5:$B$154,"<="&H$5+6)>0,"●",IF(AND(H$5<=Estrategias!$I$10,H$5+6>=Estrategias!$H$10),"■","")) -> ■ | I21: =IF(COUNTIFS(Eventos!$A$5:$A$154,$A21,Eventos!$B$5:$B$154,">="&I$5,Eventos!$B$5:$B$154,"<="&I$5+6)>0,"●",IF(AND(I$5<=Estrategias!$I$10,I$5+6>=Estrategias!$H$10),"■","")) | J21: =IF(COUNTIFS(Eventos!$A$5:$A$154,$A21,Eventos!$B$5:$B$154,">="&J$5,Eventos!$B$5:$B$154,"<="&J$5+6)>0,"●",IF(AND(J$5<=Estrategias!$I$10,J$5+6>=Estrategias!$H$10),"■","")) | K21: =IF(COUNTIFS(Eventos!$A$5:$A$154,$A21,Eventos!$B$5:$B$154,">="&K$5,Eventos!$B$5:$B$154,"<="&K$5+6)>0,"●",IF(AND(K$5<=Estrategias!$I$10,K$5+6>=Estrategias!$H$10),"■","")) | ... AA21: =IF(COUNTIFS(Eventos!$A$5:$A$154,$A21,Eventos!$B$5:$B$154,">="&AA$5,Eventos!$B$5:$B$154,"<="&AA$5+6)>0,"●",IF(AND(AA$5<=Estrategias!$I$10,AA$5+6>=Estrategias!$H$10),"■",""))
A22: =Estrategias!A11 -> E7 | B22: =Estrategias!C11 -> Promoción en calle con registro de contactos | C22: =Estrategias!B11 -> Media | D22: =IF(COUNTIFS(Eventos!$A$5:$A$154,$A22,Eventos!$B$5:$B$154,">="&D$5,Eventos!$B$5:$B$154,"<="&D$5+6)>0,"●",IF(AND(D$5<=Estrategias!$I$11,D$5+6>=Estrategias!$H$11),"■","")) | E22: =IF(COUNTIFS(Eventos!$A$5:$A$154,$A22,Eventos!$B$5:$B$154,">="&E$5,Eventos!$B$5:$B$154,"<="&E$5+6)>0,"●",IF(AND(E$5<=Estrategias!$I$11,E$5+6>=Estrategias!$H$11),"■","")) | F22: =IF(COUNTIFS(Eventos!$A$5:$A$154,$A22,Eventos!$B$5:$B$154,">="&F$5,Eventos!$B$5:$B$154,"<="&F$5+6)>0,"●",IF(AND(F$5<=Estrategias!$I$11,F$5+6>=Estrategias!$H$11),"■","")) -> ● | G22: =IF(COUNTIFS(Eventos!$A$5:$A$154,$A22,Eventos!$B$5:$B$154,">="&G$5,Eventos!$B$5:$B$154,"<="&G$5+6)>0,"●",IF(AND(G$5<=Estrategias!$I$11,G$5+6>=Estrategias!$H$11),"■","")) -> ■ | H22: =IF(COUNTIFS(Eventos!$A$5:$A$154,$A22,Eventos!$B$5:$B$154,">="&H$5,Eventos!$B$5:$B$154,"<="&H$5+6)>0,"●",IF(AND(H$5<=Estrategias!$I$11,H$5+6>=Estrategias!$H$11),"■","")) -> ■ | I22: =IF(COUNTIFS(Eventos!$A$5:$A$154,$A22,Eventos!$B$5:$B$154,">="&I$5,Eventos!$B$5:$B$154,"<="&I$5+6)>0,"●",IF(AND(I$5<=Estrategias!$I$11,I$5+6>=Estrategias!$H$11),"■","")) -> ■ | J22: =IF(COUNTIFS(Eventos!$A$5:$A$154,$A22,Eventos!$B$5:$B$154,">="&J$5,Eventos!$B$5:$B$154,"<="&J$5+6)>0,"●",IF(AND(J$5<=Estrategias!$I$11,J$5+6>=Estrategias!$H$11),"■","")) -> ■ | K22: =IF(COUNTIFS(Eventos!$A$5:$A$154,$A22,Eventos!$B$5:$B$154,">="&K$5,Eventos!$B$5:$B$154,"<="&K$5+6)>0,"●",IF(AND(K$5<=Estrategias!$I$11,K$5+6>=Estrategias!$H$11),"■","")) -> ■ | ... AA22: =IF(COUNTIFS(Eventos!$A$5:$A$154,$A22,Eventos!$B$5:$B$154,">="&AA$5,Eventos!$B$5:$B$154,"<="&AA$5+6)>0,"●",IF(AND(AA$5<=Estrategias!$I$11,AA$5+6>=Estrategias!$H$11),"■",""))
A23: =Estrategias!A12 -> E8 | B23: =Estrategias!C12 -> Curso intensivo de invierno (evaluar) | C23: =Estrategias!B12 -> Media | D23: =IF(COUNTIFS(Eventos!$A$5:$A$154,$A23,Eventos!$B$5:$B$154,">="&D$5,Eventos!$B$5:$B$154,"<="&D$5+6)>0,"●",IF(AND(D$5<=Estrategias!$I$12,D$5+6>=Estrategias!$H$12),"■","")) | E23: =IF(COUNTIFS(Eventos!$A$5:$A$154,$A23,Eventos!$B$5:$B$154,">="&E$5,Eventos!$B$5:$B$154,"<="&E$5+6)>0,"●",IF(AND(E$5<=Estrategias!$I$12,E$5+6>=Estrategias!$H$12),"■","")) | F23: =IF(COUNTIFS(Eventos!$A$5:$A$154,$A23,Eventos!$B$5:$B$154,">="&F$5,Eventos!$B$5:$B$154,"<="&F$5+6)>0,"●",IF(AND(F$5<=Estrategias!$I$12,F$5+6>=Estrategias!$H$12),"■","")) | G23: =IF(COUNTIFS(Eventos!$A$5:$A$154,$A23,Eventos!$B$5:$B$154,">="&G$5,Eventos!$B$5:$B$154,"<="&G$5+6)>0,"●",IF(AND(G$5<=Estrategias!$I$12,G$5+6>=Estrategias!$H$12),"■","")) | H23: =IF(COUNTIFS(Eventos!$A$5:$A$154,$A23,Eventos!$B$5:$B$154,">="&H$5,Eventos!$B$5:$B$154,"<="&H$5+6)>0,"●",IF(AND(H$5<=Estrategias!$I$12,H$5+6>=Estrategias!$H$12),"■","")) -> ● | I23: =IF(COUNTIFS(Eventos!$A$5:$A$154,$A23,Eventos!$B$5:$B$154,">="&I$5,Eventos!$B$5:$B$154,"<="&I$5+6)>0,"●",IF(AND(I$5<=Estrategias!$I$12,I$5+6>=Estrategias!$H$12),"■","")) | J23: =IF(COUNTIFS(Eventos!$A$5:$A$154,$A23,Eventos!$B$5:$B$154,">="&J$5,Eventos!$B$5:$B$154,"<="&J$5+6)>0,"●",IF(AND(J$5<=Estrategias!$I$12,J$5+6>=Estrategias!$H$12),"■","")) | K23: =IF(COUNTIFS(Eventos!$A$5:$A$154,$A23,Eventos!$B$5:$B$154,">="&K$5,Eventos!$B$5:$B$154,"<="&K$5+6)>0,"●",IF(AND(K$5<=Estrategias!$I$12,K$5+6>=Estrategias!$H$12),"■","")) | ... AA23: =IF(COUNTIFS(Eventos!$A$5:$A$154,$A23,Eventos!$B$5:$B$154,">="&AA$5,Eventos!$B$5:$B$154,"<="&AA$5+6)>0,"●",IF(AND(AA$5<=Estrategias!$I$12,AA$5+6>=Estrategias!$H$12),"■",""))
A24: =Estrategias!A13 -> E9 | B24: =Estrategias!C13 -> Convenios con empresas e instituciones cercanas | C24: =Estrategias!B13 -> Baja | D24: =IF(COUNTIFS(Eventos!$A$5:$A$154,$A24,Eventos!$B$5:$B$154,">="&D$5,Eventos!$B$5:$B$154,"<="&D$5+6)>0,"●",IF(AND(D$5<=Estrategias!$I$13,D$5+6>=Estrategias!$H$13),"■","")) | E24: =IF(COUNTIFS(Eventos!$A$5:$A$154,$A24,Eventos!$B$5:$B$154,">="&E$5,Eventos!$B$5:$B$154,"<="&E$5+6)>0,"●",IF(AND(E$5<=Estrategias!$I$13,E$5+6>=Estrategias!$H$13),"■","")) | F24: =IF(COUNTIFS(Eventos!$A$5:$A$154,$A24,Eventos!$B$5:$B$154,">="&F$5,Eventos!$B$5:$B$154,"<="&F$5+6)>0,"●",IF(AND(F$5<=Estrategias!$I$13,F$5+6>=Estrategias!$H$13),"■","")) | G24: =IF(COUNTIFS(Eventos!$A$5:$A$154,$A24,Eventos!$B$5:$B$154,">="&G$5,Eventos!$B$5:$B$154,"<="&G$5+6)>0,"●",IF(AND(G$5<=Estrategias!$I$13,G$5+6>=Estrategias!$H$13),"■","")) | H24: =IF(COUNTIFS(Eventos!$A$5:$A$154,$A24,Eventos!$B$5:$B$154,">="&H$5,Eventos!$B$5:$B$154,"<="&H$5+6)>0,"●",IF(AND(H$5<=Estrategias!$I$13,H$5+6>=Estrategias!$H$13),"■","")) | I24: =IF(COUNTIFS(Eventos!$A$5:$A$154,$A24,Eventos!$B$5:$B$154,">="&I$5,Eventos!$B$5:$B$154,"<="&I$5+6)>0,"●",IF(AND(I$5<=Estrategias!$I$13,I$5+6>=Estrategias!$H$13),"■","")) | J24: =IF(COUNTIFS(Eventos!$A$5:$A$154,$A24,Eventos!$B$5:$B$154,">="&J$5,Eventos!$B$5:$B$154,"<="&J$5+6)>0,"●",IF(AND(J$5<=Estrategias!$I$13,J$5+6>=Estrategias!$H$13),"■","")) | K24: =IF(COUNTIFS(Eventos!$A$5:$A$154,$A24,Eventos!$B$5:$B$154,">="&K$5,Eventos!$B$5:$B$154,"<="&K$5+6)>0,"●",IF(AND(K$5<=Estrategias!$I$13,K$5+6>=Estrategias!$H$13),"■","")) | ... AA24: =IF(COUNTIFS(Eventos!$A$5:$A$154,$A24,Eventos!$B$5:$B$154,">="&AA$5,Eventos!$B$5:$B$154,"<="&AA$5+6)>0,"●",IF(AND(AA$5<=Estrategias!$I$13,AA$5+6>=Estrategias!$H$13),"■",""))
A25: =Estrategias!A14 -> E10 | B25: =Estrategias!C14 -> Segundo idioma y hermanos para familias actuales | C25: =Estrategias!B14 -> Baja | D25: =IF(COUNTIFS(Eventos!$A$5:$A$154,$A25,Eventos!$B$5:$B$154,">="&D$5,Eventos!$B$5:$B$154,"<="&D$5+6)>0,"●",IF(AND(D$5<=Estrategias!$I$14,D$5+6>=Estrategias!$H$14),"■","")) | E25: =IF(COUNTIFS(Eventos!$A$5:$A$154,$A25,Eventos!$B$5:$B$154,">="&E$5,Eventos!$B$5:$B$154,"<="&E$5+6)>0,"●",IF(AND(E$5<=Estrategias!$I$14,E$5+6>=Estrategias!$H$14),"■","")) | F25: =IF(COUNTIFS(Eventos!$A$5:$A$154,$A25,Eventos!$B$5:$B$154,">="&F$5,Eventos!$B$5:$B$154,"<="&F$5+6)>0,"●",IF(AND(F$5<=Estrategias!$I$14,F$5+6>=Estrategias!$H$14),"■","")) | G25: =IF(COUNTIFS(Eventos!$A$5:$A$154,$A25,Eventos!$B$5:$B$154,">="&G$5,Eventos!$B$5:$B$154,"<="&G$5+6)>0,"●",IF(AND(G$5<=Estrategias!$I$14,G$5+6>=Estrategias!$H$14),"■","")) | H25: =IF(COUNTIFS(Eventos!$A$5:$A$154,$A25,Eventos!$B$5:$B$154,">="&H$5,Eventos!$B$5:$B$154,"<="&H$5+6)>0,"●",IF(AND(H$5<=Estrategias!$I$14,H$5+6>=Estrategias!$H$14),"■","")) | I25: =IF(COUNTIFS(Eventos!$A$5:$A$154,$A25,Eventos!$B$5:$B$154,">="&I$5,Eventos!$B$5:$B$154,"<="&I$5+6)>0,"●",IF(AND(I$5<=Estrategias!$I$14,I$5+6>=Estrategias!$H$14),"■","")) | J25: =IF(COUNTIFS(Eventos!$A$5:$A$154,$A25,Eventos!$B$5:$B$154,">="&J$5,Eventos!$B$5:$B$154,"<="&J$5+6)>0,"●",IF(AND(J$5<=Estrategias!$I$14,J$5+6>=Estrategias!$H$14),"■","")) | K25: =IF(COUNTIFS(Eventos!$A$5:$A$154,$A25,Eventos!$B$5:$B$154,">="&K$5,Eventos!$B$5:$B$154,"<="&K$5+6)>0,"●",IF(AND(K$5<=Estrategias!$I$14,K$5+6>=Estrategias!$H$14),"■","")) | ... AA25: =IF(COUNTIFS(Eventos!$A$5:$A$154,$A25,Eventos!$B$5:$B$154,">="&AA$5,Eventos!$B$5:$B$154,"<="&AA$5+6)>0,"●",IF(AND(AA$5<=Estrategias!$I$14,AA$5+6>=Estrategias!$H$14),"■",""))
B27: Fuentes de fechas: calendario escolar SEP 2026-2027 publicado en el DOF (vacaciones de invierno 21-dic a 6-ene; Semana Santa 22-mar a 2-abr) y fechas del Buen Fin 2026 (13 al 17 de noviembre) reportadas por prensa nacional. Columnas AD y AE: fechas de inicio y fin de cada fecha clave.

Sheet Resultados por estrategia
A1: Resultados por estrategia (se alimenta de la hoja Eventos)
A2: Para las estrategias sin eventos (E1, E2, E4), capturar los totales mensuales como una fila en Eventos con la fecha de corte.
A4: ID | B4: Estrategia | C4: Estatus | D4: Eventos realizados | E4: Contactos | F4: Con teléfono | G4: CM agendadas | H4: CM realizadas | I4: Inscritos | J4: Costo real | K4: Costo por inscrito | L4: % contactos con teléfono | M4: Cierre tras CM
A5: =Estrategias!A5 -> E1 | B5: =Estrategias!C5 -> Recuperar prospectos que ya asistieron o ya escribieron | C5: =Estrategias!S5 -> Propuesta | D5: =COUNTIFS(Eventos!$A$5:$A$154,A5,Eventos!$F$5:$F$154,"Realizada") -> 0 | E5: =SUMIFS(Eventos!$G$5:$G$154,Eventos!$A$5:$A$154,A5) -> 0 | F5: =SUMIFS(Eventos!$H$5:$H$154,Eventos!$A$5:$A$154,A5) -> 0 | G5: =SUMIFS(Eventos!$I$5:$I$154,Eventos!$A$5:$A$154,A5) -> 0 | H5: =SUMIFS(Eventos!$J$5:$J$154,Eventos!$A$5:$A$154,A5) -> 0 | I5: =SUMIFS(Eventos!$K$5:$K$154,Eventos!$A$5:$A$154,A5) -> 0 | J5: =SUMIFS(Eventos!$L$5:$L$154,Eventos!$A$5:$A$154,A5) -> 0 | K5: =IF(I5=0,"",J5/I5) | L5: =IF(E5=0,"",F5/E5) | M5: =IF(H5=0,"",I5/H5)
A6: =Estrategias!A6 -> E2 | B6: =Estrategias!C6 -> Programa de recomendación de alumnos y padres | C6: =Estrategias!S6 -> Propuesta | D6: =COUNTIFS(Eventos!$A$5:$A$154,A6,Eventos!$F$5:$F$154,"Realizada") -> 0 | E6: =SUMIFS(Eventos!$G$5:$G$154,Eventos!$A$5:$A$154,A6) -> 0 | F6: =SUMIFS(Eventos!$H$5:$H$154,Eventos!$A$5:$A$154,A6) -> 0 | G6: =SUMIFS(Eventos!$I$5:$I$154,Eventos!$A$5:$A$154,A6) -> 0 | H6: =SUMIFS(Eventos!$J$5:$J$154,Eventos!$A$5:$A$154,A6) -> 0 | I6: =SUMIFS(Eventos!$K$5:$K$154,Eventos!$A$5:$A$154,A6) -> 0 | J6: =SUMIFS(Eventos!$L$5:$L$154,Eventos!$A$5:$A$154,A6) -> 0 | K6: =IF(I6=0,"",J6/I6) | L6: =IF(E6=0,"",F6/E6) | M6: =IF(H6=0,"",I6/H6)
A7: =Estrategias!A7 -> E3 | B7: =Estrategias!C7 -> Alianzas con escuelas cercanas: taller de inglés y beneficio para familias | C7: =Estrategias!S7 -> Propuesta | D7: =COUNTIFS(Eventos!$A$5:$A$154,A7,Eventos!$F$5:$F$154,"Realizada") -> 0 | E7: =SUMIFS(Eventos!$G$5:$G$154,Eventos!$A$5:$A$154,A7) -> 0 | F7: =SUMIFS(Eventos!$H$5:$H$154,Eventos!$A$5:$A$154,A7) -> 0 | G7: =SUMIFS(Eventos!$I$5:$I$154,Eventos!$A$5:$A$154,A7) -> 0 | H7: =SUMIFS(Eventos!$J$5:$J$154,Eventos!$A$5:$A$154,A7) -> 0 | I7: =SUMIFS(Eventos!$K$5:$K$154,Eventos!$A$5:$A$154,A7) -> 0 | J7: =SUMIFS(Eventos!$L$5:$L$154,Eventos!$A$5:$A$154,A7) -> 0 | K7: =IF(I7=0,"",J7/I7) | L7: =IF(E7=0,"",F7/E7) | M7: =IF(H7=0,"",I7/H7)
A8: =Estrategias!A8 -> E4 | B8: =Estrategias!C8 -> Recuperar bajas temporales y exalumnos para enero | C8: =Estrategias!S8 -> Propuesta | D8: =COUNTIFS(Eventos!$A$5:$A$154,A8,Eventos!$F$5:$F$154,"Realizada") -> 0 | E8: =SUMIFS(Eventos!$G$5:$G$154,Eventos!$A$5:$A$154,A8) -> 0 | F8: =SUMIFS(Eventos!$H$5:$H$154,Eventos!$A$5:$A$154,A8) -> 0 | G8: =SUMIFS(Eventos!$I$5:$I$154,Eventos!$A$5:$A$154,A8) -> 0 | H8: =SUMIFS(Eventos!$J$5:$J$154,Eventos!$A$5:$A$154,A8) -> 0 | I8: =SUMIFS(Eventos!$K$5:$K$154,Eventos!$A$5:$A$154,A8) -> 0 | J8: =SUMIFS(Eventos!$L$5:$L$154,Eventos!$A$5:$A$154,A8) -> 0 | K8: =IF(I8=0,"",J8/I8) | L8: =IF(E8=0,"",F8/E8) | M8: =IF(H8=0,"",I8/H8)
A9: =Estrategias!A9 -> E5 | B9: =Estrategias!C9 -> Clase abierta de sábado para familias y recomendados | C9: =Estrategias!S9 -> Propuesta | D9: =COUNTIFS(Eventos!$A$5:$A$154,A9,Eventos!$F$5:$F$154,"Realizada") -> 0 | E9: =SUMIFS(Eventos!$G$5:$G$154,Eventos!$A$5:$A$154,A9) -> 0 | F9: =SUMIFS(Eventos!$H$5:$H$154,Eventos!$A$5:$A$154,A9) -> 0 | G9: =SUMIFS(Eventos!$I$5:$I$154,Eventos!$A$5:$A$154,A9) -> 0 | H9: =SUMIFS(Eventos!$J$5:$J$154,Eventos!$A$5:$A$154,A9) -> 0 | I9: =SUMIFS(Eventos!$K$5:$K$154,Eventos!$A$5:$A$154,A9) -> 0 | J9: =SUMIFS(Eventos!$L$5:$L$154,Eventos!$A$5:$A$154,A9) -> 0 | K9: =IF(I9=0,"",J9/I9) | L9: =IF(E9=0,"",F9/E9) | M9: =IF(H9=0,"",I9/H9)
A10: =Estrategias!A10 -> E6 | B10: =Estrategias!C10 -> Visibilidad física de la academia (tránsito) | C10: =Estrategias!S10 -> Propuesta | D10: =COUNTIFS(Eventos!$A$5:$A$154,A10,Eventos!$F$5:$F$154,"Realizada") -> 0 | E10: =SUMIFS(Eventos!$G$5:$G$154,Eventos!$A$5:$A$154,A10) -> 0 | F10: =SUMIFS(Eventos!$H$5:$H$154,Eventos!$A$5:$A$154,A10) -> 0 | G10: =SUMIFS(Eventos!$I$5:$I$154,Eventos!$A$5:$A$154,A10) -> 0 | H10: =SUMIFS(Eventos!$J$5:$J$154,Eventos!$A$5:$A$154,A10) -> 0 | I10: =SUMIFS(Eventos!$K$5:$K$154,Eventos!$A$5:$A$154,A10) -> 0 | J10: =SUMIFS(Eventos!$L$5:$L$154,Eventos!$A$5:$A$154,A10) -> 0 | K10: =IF(I10=0,"",J10/I10) | L10: =IF(E10=0,"",F10/E10) | M10: =IF(H10=0,"",I10/H10)
A11: =Estrategias!A11 -> E7 | B11: =Estrategias!C11 -> Promoción en calle con registro de contactos | C11: =Estrategias!S11 -> Propuesta | D11: =COUNTIFS(Eventos!$A$5:$A$154,A11,Eventos!$F$5:$F$154,"Realizada") -> 0 | E11: =SUMIFS(Eventos!$G$5:$G$154,Eventos!$A$5:$A$154,A11) -> 0 | F11: =SUMIFS(Eventos!$H$5:$H$154,Eventos!$A$5:$A$154,A11) -> 0 | G11: =SUMIFS(Eventos!$I$5:$I$154,Eventos!$A$5:$A$154,A11) -> 0 | H11: =SUMIFS(Eventos!$J$5:$J$154,Eventos!$A$5:$A$154,A11) -> 0 | I11: =SUMIFS(Eventos!$K$5:$K$154,Eventos!$A$5:$A$154,A11) -> 0 | J11: =SUMIFS(Eventos!$L$5:$L$154,Eventos!$A$5:$A$154,A11) -> 0 | K11: =IF(I11=0,"",J11/I11) | L11: =IF(E11=0,"",F11/E11) | M11: =IF(H11=0,"",I11/H11)
A12: =Estrategias!A12 -> E8 | B12: =Estrategias!C12 -> Curso intensivo de invierno (evaluar) | C12: =Estrategias!S12 -> Propuesta | D12: =COUNTIFS(Eventos!$A$5:$A$154,A12,Eventos!$F$5:$F$154,"Realizada") -> 0 | E12: =SUMIFS(Eventos!$G$5:$G$154,Eventos!$A$5:$A$154,A12) -> 0 | F12: =SUMIFS(Eventos!$H$5:$H$154,Eventos!$A$5:$A$154,A12) -> 0 | G12: =SUMIFS(Eventos!$I$5:$I$154,Eventos!$A$5:$A$154,A12) -> 0 | H12: =SUMIFS(Eventos!$J$5:$J$154,Eventos!$A$5:$A$154,A12) -> 0 | I12: =SUMIFS(Eventos!$K$5:$K$154,Eventos!$A$5:$A$154,A12) -> 0 | J12: =SUMIFS(Eventos!$L$5:$L$154,Eventos!$A$5:$A$154,A12) -> 0 | K12: =IF(I12=0,"",J12/I12) | L12: =IF(E12=0,"",F12/E12) | M12: =IF(H12=0,"",I12/H12)
A13: =Estrategias!A13 -> E9 | B13: =Estrategias!C13 -> Convenios con empresas e instituciones cercanas | C13: =Estrategias!S13 -> Propuesta | D13: =COUNTIFS(Eventos!$A$5:$A$154,A13,Eventos!$F$5:$F$154,"Realizada") -> 0 | E13: =SUMIFS(Eventos!$G$5:$G$154,Eventos!$A$5:$A$154,A13) -> 0 | F13: =SUMIFS(Eventos!$H$5:$H$154,Eventos!$A$5:$A$154,A13) -> 0 | G13: =SUMIFS(Eventos!$I$5:$I$154,Eventos!$A$5:$A$154,A13) -> 0 | H13: =SUMIFS(Eventos!$J$5:$J$154,Eventos!$A$5:$A$154,A13) -> 0 | I13: =SUMIFS(Eventos!$K$5:$K$154,Eventos!$A$5:$A$154,A13) -> 0 | J13: =SUMIFS(Eventos!$L$5:$L$154,Eventos!$A$5:$A$154,A13) -> 0 | K13: =IF(I13=0,"",J13/I13) | L13: =IF(E13=0,"",F13/E13) | M13: =IF(H13=0,"",I13/H13)
A14: =Estrategias!A14 -> E10 | B14: =Estrategias!C14 -> Segundo idioma y hermanos para familias actuales | C14: =Estrategias!S14 -> Propuesta | D14: =COUNTIFS(Eventos!$A$5:$A$154,A14,Eventos!$F$5:$F$154,"Realizada") -> 0 | E14: =SUMIFS(Eventos!$G$5:$G$154,Eventos!$A$5:$A$154,A14) -> 0 | F14: =SUMIFS(Eventos!$H$5:$H$154,Eventos!$A$5:$A$154,A14) -> 0 | G14: =SUMIFS(Eventos!$I$5:$I$154,Eventos!$A$5:$A$154,A14) -> 0 | H14: =SUMIFS(Eventos!$J$5:$J$154,Eventos!$A$5:$A$154,A14) -> 0 | I14: =SUMIFS(Eventos!$K$5:$K$154,Eventos!$A$5:$A$154,A14) -> 0 | J14: =SUMIFS(Eventos!$L$5:$L$154,Eventos!$A$5:$A$154,A14) -> 0 | K14: =IF(I14=0,"",J14/I14) | L14: =IF(E14=0,"",F14/E14) | M14: =IF(H14=0,"",I14/H14)
